arcor2_arserver/VERSION
arcor2_arserver/__init__.py
arcor2_arserver/checks.py
arcor2_arserver/common.py
arcor2_arserver/decorators.py
arcor2_arserver/events.py
arcor2_arserver/execution.py
arcor2_arserver/globals.py
arcor2_arserver/helpers.py
arcor2_arserver/models.py
arcor2_arserver/notifications.py
arcor2_arserver/objects_actions.py
arcor2_arserver/project.py
arcor2_arserver/py.typed
arcor2_arserver/robot.py
arcor2_arserver/scene.py
arcor2_arserver/settings.py
arcor2_arserver/user.py
arcor2_arserver/clients/__init__.py
arcor2_arserver/clients/project_service.py
arcor2_arserver/lock/__init__.py
arcor2_arserver/lock/common.py
arcor2_arserver/lock/exceptions.py
arcor2_arserver/lock/lock.py
arcor2_arserver/lock/notifications.py
arcor2_arserver/lock/structures.py
arcor2_arserver/object_types/__init__.py
arcor2_arserver/object_types/data.py
arcor2_arserver/object_types/source.py
arcor2_arserver/object_types/utils.py
arcor2_arserver/rpc/__init__.py
arcor2_arserver/rpc/camera.py
arcor2_arserver/rpc/execution.py
arcor2_arserver/rpc/lock.py
arcor2_arserver/rpc/objects.py
arcor2_arserver/rpc/project.py
arcor2_arserver/rpc/robot.py
arcor2_arserver/rpc/scene.py
arcor2_arserver/rpc/user.py
arcor2_arserver/scripts/__init__.py
arcor2_arserver/scripts/arserver.py
arcor2_arserver/scripts/broadcaster.py
arcor2_arserver-1.3.0.dist-info/METADATA
arcor2_arserver-1.3.0.dist-info/WHEEL
arcor2_arserver-1.3.0.dist-info/entry_points.txt
arcor2_arserver-1.3.0.dist-info/namespace_packages.txt
arcor2_arserver-1.3.0.dist-info/top_level.txt
arcor2_arserver-1.3.0.dist-info/RECORD
