Metadata-Version: 2.1
Name: arcor2-arserver
Version: 1.3.0
Summary: ARCOR2 ARServer
Author: Robo@FIT
Author-email: imaterna@fit.vut.cz
License: LGPL
Classifier: Development Status :: 3 - Alpha
Classifier: Intended Audience :: Developers
Classifier: Topic :: Software Development :: Build Tools
Classifier: License :: OSI Approved :: GNU Lesser General Public License v3 (LGPLv3)
Classifier: Programming Language :: Python :: 3.11
Classifier: Natural Language :: English
Classifier: Topic :: Scientific/Engineering
Requires-Python: ==3.11.*
Requires-Dist: Flask (~=3.0.3)
Requires-Dist: aiofiles (~=23.2.1)
Requires-Dist: aiologger (~=0.7.0)
Requires-Dist: aiorun (~=2024.5.1)
Requires-Dist: apispec-webframeworks (~=1.1.0)
Requires-Dist: apispec[yaml] (~=6.6.1)
Requires-Dist: arcor2-arserver-data (~=1.1.0)
Requires-Dist: arcor2-build-data (~=1.1.0)
Requires-Dist: arcor2-calibration-data (~=1.1.0)
Requires-Dist: arcor2-execution-data (~=1.2.0)
Requires-Dist: arcor2-runtime (~=1.4.0)
Requires-Dist: arcor2 (~=1.5.0)
Requires-Dist: dataclasses-jsonschema[apispec,fast-dateparsing,fast-validation] (~=2.16.0)
Requires-Dist: lru-dict (~=1.3.0)
Requires-Dist: numpy-quaternion[numba,scipy] (~=2023.0.3)
Requires-Dist: numpy (~=1.26.4)
Requires-Dist: pyhumps (==3.8.0)
Requires-Dist: setuptools (~=70.0.0)
Requires-Dist: types-aiofiles (==23.2.0.20240403)
Requires-Dist: typing-inspect (~=0.9.0)
Requires-Dist: websockets (~=12.0)
